remo-0.6.1.data/scripts/remo
remo_app/CHANGELOG.md
remo_app/LICENSE
remo_app/README.md
remo_app/__init__.py
remo_app/__main__.py
remo_app/version.py
remo_app/cmd/__init__.py
remo_app/cmd/checker.py
remo_app/cmd/cmd.py
remo_app/cmd/config.py
remo_app/cmd/db.py
remo_app/cmd/downloader.py
remo_app/cmd/fmt.py
remo_app/cmd/installer.py
remo_app/cmd/killer.py
remo_app/cmd/log.py
remo_app/cmd/logo.py
remo_app/cmd/pip.py
remo_app/cmd/postgres.py
remo_app/cmd/runtime.py
remo_app/cmd/server.py
remo_app/cmd/shell.py
remo_app/cmd/uuid.py
remo_app/cmd/version.py
remo_app/cmd/viewer/__init__.py
remo_app/cmd/viewer/browser.py
remo_app/cmd/viewer/electron.py
remo_app/config/__init__.py
remo_app/config/config.py
remo_app/config/standalone/__init__.py
remo_app/config/standalone/settings.py
remo_app/config/standalone/urls.py
remo_app/config/standalone/wsgi.py
remo_app/remo/__init__.py
remo_app/remo/apps.py
remo_app/remo/api/__init__.py
remo_app/remo/api/auth.py
remo_app/remo/api/constants.py
remo_app/remo/api/middleware.py
remo_app/remo/api/permissions.py
remo_app/remo/api/shortcuts.py
remo_app/remo/api/urls.py
remo_app/remo/api/utils.py
remo_app/remo/api/viewsets.py
remo_app/remo/api/serializers/__init__.py
remo_app/remo/api/serializers/annotation_serializer.py
remo_app/remo/api/serializers/annotation_set_insights_serializer.py
remo_app/remo/api/serializers/annotation_set_serializer.py
remo_app/remo/api/serializers/autocomplete_serializer.py
remo_app/remo/api/serializers/common_class_serializer.py
remo_app/remo/api/serializers/dataset_search_serializer.py
remo_app/remo/api/serializers/dataset_serializer.py
remo_app/remo/api/serializers/feedback_serializer.py
remo_app/remo/api/serializers/folder_serializer.py
remo_app/remo/api/serializers/image_serializer.py
remo_app/remo/api/serializers/license_serializer.py
remo_app/remo/api/serializers/login_serializer.py
remo_app/remo/api/serializers/tag_serializer.py
remo_app/remo/api/serializers/task_serializer.py
remo-0.6.1.dist-info/METADATA
remo-0.6.1.dist-info/WHEEL
remo-0.6.1.dist-info/top_level.txt
remo-0.6.1.dist-info/RECORD
