Metadata-Version: 2.1
Name: remo
Version: 0.6.1
Summary: Remo, a webapp to manage datasets and annotations for Computer Vision
Home-page: https://remo.ai
Author: Rediscovery.io
Author-email: hello@remo.ai
License: Creative Commons Attribution-NoDerivatives 4.0 International Public License (CC BY-ND 4.0)
Platform: UNKNOWN
Classifier: Environment :: Console
Classifier: Intended Audience :: Developers
Classifier: Intended Audience :: Science/Research
Classifier: Operating System :: POSIX :: Linux
Classifier: Operating System :: MacOS :: MacOS X
Classifier: Operating System :: Microsoft :: Windows
Classifier: Programming Language :: Python :: 3
Classifier: Programming Language :: Python :: 3.6
Classifier: Programming Language :: Python :: 3.7
Classifier: Programming Language :: Python :: 3.8
Classifier: Topic :: Scientific/Engineering
Requires-Python: >=3.6
Requires-Dist: certifi
Requires-Dist: cryptography (>=2.8)
Requires-Dist: iso8601 (==0.1.12)
Requires-Dist: remo-python (>=0.1.14)
Requires-Dist: psutil (==5.6.7)
Requires-Dist: ijson (==2.6.1)
Requires-Dist: pyvips (==2.1.8)
Requires-Dist: django (==2.2.11)
Requires-Dist: django-environ (==0.4.5)
Requires-Dist: djangorestframework (==3.11.0)
Requires-Dist: djangorestframework-csv (==2.1.0)
Requires-Dist: django-filter (==2.2.0)
Requires-Dist: django-rest-auth (==0.9.5)
Requires-Dist: django-allauth (==0.41.0)
Requires-Dist: django-querysetsequence (==0.12)
Requires-Dist: django-jsonfield (==1.4.0)
Requires-Dist: drf-nested-routers (==0.91)
Requires-Dist: requests (==2.22.0)
Requires-Dist: filetype (==1.0.5)
Requires-Dist: sendgrid (==6.0.5)
Requires-Dist: waitress (==1.4.3)
Requires-Dist: django-spa (==0.3.5)
Requires-Dist: whitenoise (==5.0.1)
Requires-Dist: typer (==0.1.1)
